catlyst/__init__.py
catlyst/school.py
catlyst-1.dist-info/METADATA
catlyst-1.dist-info/WHEEL
catlyst-1.dist-info/top_level.txt
catlyst-1.dist-info/RECORD
